{"openapi":"3.0.1","info":{"title":"Ukids admin service API","description":"Ukids admin service의 API입니다.","license":{"name":"Apache 2.0","url":"http://springdoc.org"},"version":"v0.0.1"},"externalDocs":{"description":"SpringShop Wiki Documentation","url":"https://springshop.wiki.github.org/docs"},"servers":[{"url":"http://localhost:7071","description":"Generated server url"}],"tags":[{"name":"Session Controller","description":"Session 컨트롤러"},{"name":"Sample Controller","description":"Sample 컨트롤러"}],"paths":{"/v1/samples/{name}":{"get":{"tags":["Sample Controller"],"summary":"샘플목록조회","description":"이름 like로 샘플 목록을 조회한다.","operationId":"retrieveSamples","parameters":[{"name":"name","in":"path","description":"이름","required":true,"schema":{"type":"string"},"example":"경종"}],"responses":{"404":{"description":"Not Found","content":{"*/*":{"schema":{"type":"object"}}}},"200":{"description":"OK","content":{"application/json":{"schema":{"$ref":"#/components/schemas/CommonReturnDtoListSampleDto"}}}}}}},"/v1/sample":{"post":{"tags":["Sample Controller"],"summary":"샘플생성","description":"샘플을 생성 한다.","operationId":"createSample","requestBody":{"content":{"application/json":{"schema":{"$ref":"#/components/schemas/SampleDto"}}},"required":true},"responses":{"404":{"description":"Not Found","content":{"*/*":{"schema":{"type":"object"}}}},"200":{"description":"OK","content":{"application/json":{"schema":{"$ref":"#/components/schemas/CommonReturnDtoCommonCUDQueryReturnDto"}}}}}}},"/v1/samples":{"get":{"tags":["Sample Controller"],"summary":"전체샘플목록조회","description":"전체 샘플 목록을 조회한다.","operationId":"retrieveSampleAll","responses":{"404":{"description":"Not Found","content":{"*/*":{"schema":{"type":"object"}}}},"200":{"description":"OK","content":{"application/json":{"schema":{"$ref":"#/components/schemas/CommonReturnDtoListSampleDto"}}}}}}},"/v1/sample/{id}":{"put":{"tags":["Sample Controller"],"summary":"샘플수정","description":"샘플을 수정한다","operationId":"updateContentsComments","parameters":[{"name":"id","in":"path","description":"아이디","required":true,"schema":{"type":"string"},"example":1}],"requestBody":{"content":{"application/json":{"schema":{"$ref":"#/components/schemas/SampleDto"}}},"required":true},"responses":{"404":{"description":"Not Found","content":{"*/*":{"schema":{"type":"object"}}}},"200":{"description":"OK","content":{"application/json":{"schema":{"$ref":"#/components/schemas/CommonReturnDtoCommonCUDQueryReturnDto"}}}}}},"delete":{"tags":["Sample Controller"],"summary":"샘플 삭제","description":"샘플을 삭제한다.","operationId":"deleteContentsComments","parameters":[{"name":"id","in":"path","description":"아이디","required":true,"schema":{"type":"string"},"example":1}],"responses":{"404":{"description":"Not Found","content":{"*/*":{"schema":{"type":"object"}}}},"200":{"description":"OK","content":{"application/json":{"schema":{"$ref":"#/components/schemas/CommonReturnDtoCommonCUDQueryReturnDto"}}}}}}},"/v1/sample/detail":{"get":{"tags":["Sample Controller"],"summary":"샘플상세조회","description":"아이디로 샘플 목록을 조회한다.","operationId":"retrieveSampleDetail","parameters":[{"name":"id","in":"query","description":"아이디","required":true,"schema":{"type":"string"},"example":1}],"responses":{"404":{"description":"Not Found","content":{"*/*":{"schema":{"type":"object"}}}},"200":{"description":"OK","content":{"application/json":{"schema":{"$ref":"#/components/schemas/CommonReturnDtoSampleDto"}}}}}}},"/v1/session":{"get":{"tags":["Session Controller"],"summary":"세션조회","description":"현재 세션정보를 조회한다.","operationId":"sessionHealthy","responses":{"404":{"description":"Not Found","content":{"*/*":{"schema":{"type":"object"}}}},"200":{"description":"OK","content":{"*/*":{"schema":{"$ref":"#/components/schemas/CommonReturnDtoSessionDto"}}}}}},"post":{"tags":["Session Controller"],"summary":"로그인","description":"로그인 하고 세션정보를 응답한다.","operationId":"login","requestBody":{"content":{"application/json":{"schema":{"$ref":"#/components/schemas/SessionDto"}}},"required":true},"responses":{"404":{"description":"Not Found","content":{"*/*":{"schema":{"type":"object"}}}},"200":{"description":"OK","content":{"application/json":{"schema":{"$ref":"#/components/schemas/CommonReturnDtoSessionDto"}}}}}},"delete":{"tags":["Session Controller"],"summary":"로그아웃","description":"로그아웃한다.","operationId":"logout","responses":{"404":{"description":"Not Found","content":{"*/*":{"schema":{"type":"object"}}}},"200":{"description":"OK","content":{"*/*":{"schema":{"$ref":"#/components/schemas/CommonReturnDtoObject"}}}}}}},"/health":{"get":{"tags":["health-rest-controller"],"summary":"health check","description":"health check","operationId":"retrieveHealthy","responses":{"404":{"description":"Not Found","content":{"*/*":{"schema":{"type":"object"}}}},"200":{"description":"OK","content":{"application/json":{"schema":{"type":"string"}}}}}}}},"components":{"schemas":{"CommonReturnDtoListSampleDto":{"type":"object","properties":{"successOrNot":{"type":"string"},"statusCode":{"type":"string"},"data":{"type":"array","items":{"$ref":"#/components/schemas/SampleDto"}}}},"SampleDto":{"type":"object","properties":{"id":{"type":"string"},"name":{"type":"string"}},"description":"샘플 수정 요청 정보"},"CommonCUDQueryReturnDto":{"type":"object","properties":{"affectedRows":{"type":"integer","format":"int32"}}},"CommonReturnDtoCommonCUDQueryReturnDto":{"type":"object","properties":{"successOrNot":{"type":"string"},"statusCode":{"type":"string"},"data":{"$ref":"#/components/schemas/CommonCUDQueryReturnDto"}}},"CommonReturnDtoSampleDto":{"type":"object","properties":{"successOrNot":{"type":"string"},"statusCode":{"type":"string"},"data":{"$ref":"#/components/schemas/SampleDto"}}},"CommonReturnDtoSessionDto":{"type":"object","properties":{"successOrNot":{"type":"string"},"statusCode":{"type":"string"},"data":{"$ref":"#/components/schemas/SessionDto"}}},"SessionDto":{"type":"object","properties":{"sessionId":{"type":"string"},"id":{"type":"string"},"name":{"type":"string"}},"description":"로그인 요청 정보"},"CommonReturnDtoObject":{"type":"object","properties":{"successOrNot":{"type":"string"},"statusCode":{"type":"string"},"data":{"type":"object"}}}}}}